jalopy_cli/__init__.py
jalopy_cli/__main__.py
jalopy_cli/jalopy.py
jalopy_cli-1.2.dist-info/LICENSE
jalopy_cli-1.2.dist-info/METADATA
jalopy_cli-1.2.dist-info/WHEEL
jalopy_cli-1.2.dist-info/entry_points.txt
jalopy_cli-1.2.dist-info/top_level.txt
jalopy_cli-1.2.dist-info/RECORD
