Metadata-Version: 2.1
Name: jalopy-cli
Version: 1.2
Summary: Jalopy! Log vehicle maintenance via the commandline!
Author-email: espehon <espehon@gmail.com>
Project-URL: Homepage, https://github.com/espehon/jalopy-cli
Project-URL: Bug Tracker, https://github.com/espehon/jalopy-cli/issues
Classifier: Programming Language :: Python :: 3
Classifier: Development Status :: 5 - Production/Stable
Classifier: Environment :: Console
Classifier: License :: OSI Approved :: GNU General Public License v3 (GPLv3)
Classifier: Operating System :: OS Independent
Classifier: Topic :: Utilities
Requires-Python: >=3.8
License-File: LICENSE
Requires-Dist: pandas>=2.2.3
Requires-Dist: questionary>=2.0.1
